[
  {
    "thisSpecUrl": "https://www.w3.org/TR/2001/WD-css3-mediaqueries-20010517/",
    "properties": []
  },
  {
    "thisSpecUrl": "https://www.w3.org/TR/2001/WD-css3-mediaqueries-20010404/",
    "properties": []
  },
  {
    "thisSpecUrl": "https://www.w3.org/1999/06/WD-css3-iccprof-19990623",
    "properties": []
  },
  {
    "thisSpecUrl": "https://www.w3.org/TR/1999/WD-font-19990902",
    "properties": []
  },
  {
    "thisSpecUrl": "https://www.w3.org/TR/1999/WD-css3-page-19990928",
    "properties": []
  },
  {
    "thisSpecUrl": "https://www.w3.org/1999/06/WD-css3-page-19990623",
    "properties": []
  },
  {
    "thisSpecUrl": "https://www.w3.org/TR/2018/SPSD-CSS1-20180913/",
    "properties": []
  },
  {
    "thisSpecUrl": "https://www.w3.org/TR/2008/REC-CSS1-20080411/",
    "properties": []
  },
  {
    "thisSpecUrl": "https://www.w3.org/TR/1999/REC-CSS1-19990111",
    "properties": []
  },
  {
    "thisSpecUrl": "https://www.w3.org/TR/REC-CSS1-961217",
    "properties": []
  },
  {
    "thisSpecUrl": "https://www.w3.org/pub/WWW/TR/PR-CSS1",
    "properties": []
  },
  {
    "thisSpecUrl": "https://www.w3.org/pub/WWW/TR/WD-css1-960911.html",
    "properties": []
  },
  {
    "thisSpecUrl": "https://www.w3.org/pub/WWW/TR/WD-css1-960726.html",
    "properties": []
  },
  {
    "thisSpecUrl": "https://www.w3.org/pub/WWW/TR/WD-css1-960505.html",
    "properties": []
  },
  {
    "thisSpecUrl": "https://www.w3.org/pub/WWW/TR/WD-css1-960418.html",
    "properties": []
  },
  {
    "thisSpecUrl": "https://www.w3.org/pub/WWW/TR/WD-css1-960220.html",
    "properties": []
  },
  {
    "authors": [
      {
        "name": "H책kon WLie",
        "org": "howcome@w3.org",
        "link": "https://www.w3.org/pub/WWW/People/howcome/"
      },
      {
        "name": "Bert Bos",
        "org": "bert@w3.org",
        "link": "http://www.let.rug.nl/~bert/"
      }
    ],
    "thisSpecUrl": "https://www.w3.org/pub/WWW/TR/WD-css1-951222.html",
    "properties": []
  },
  {
    "authors": [
      {
        "name": "H책kon WLie",
        "org": "howcome@w3.org",
        "link": "https://www.w3.org/pub/WWW/People/howcome/"
      },
      {
        "name": "Bert Bos",
        "org": "bert@w3.org",
        "link": "http://www.let.rug.nl/~bert/"
      }
    ],
    "thisSpecUrl": "https://www.w3.org/pub/WWW/TR/WD-css1-951209.html",
    "properties": []
  },
  {
    "authors": [
      {
        "name": "H책kon WLie",
        "org": "howcome@w3.org",
        "link": "https://www.w3.org/hypertext/WWW/People/howcome/"
      },
      {
        "name": "Bert Bos",
        "org": "bert@w3.org",
        "link": "http://www.let.rug.nl/~bert/"
      }
    ],
    "thisSpecUrl": "https://www.w3.org/pub/WWW/TR/WD-css1-951123.html",
    "properties": []
  },
  {
    "authors": [
      {
        "name": "H책kon WLie",
        "org": "howcome@w3.org",
        "link": "https://www.w3.org/hypertext/WWW/People/howcome/"
      },
      {
        "name": "Bert Bos",
        "org": "bert@w3.org",
        "link": "http://www.let.rug.nl/~bert/"
      }
    ],
    "thisSpecUrl": "https://www.w3.org/pub/WWW/TR/WD-css1-951117.html",
    "properties": []
  }
]